Metadata-Version: 1.1
Name: sphinxcontrib.contributors
Version: 1.0
Summary: Show document contributors on the page
Home-page: https://github.com/miohtama/sphinxcontrib.contributors/
Author: Mikko Ohtamaa
Author-email: mikko@opensourcehacker.com
License: GPL
Keywords: Sphinx
Platform: UNKNOWN
Classifier: Programming Language :: Python
